sqlpuzzle
sqlpuzzle/_backends
sqlpuzzle/_common
sqlpuzzle/_queries
sqlpuzzle/_queryparts
