Metadata-Version: 2.1
Name: sqlpuzzle
Version: 2.2.0
Summary: Python library for writing SQL queries.
Home-page: https://github.com/horejsek/python-sqlpuzzle
Author: Michal Horejsek
Author-email: horejsekmichal@gmail.com
License: PSF
Platform: UNKNOWN
Classifier: Programming Language :: Python
Classifier: Programming Language :: Python :: 3
Classifier: License :: OSI Approved :: MIT License
Classifier: Operating System :: OS Independent
Classifier: Development Status :: 5 - Production/Stable
Classifier: Intended Audience :: Developers
Classifier: Topic :: Software Development :: Libraries :: Python Modules
Classifier: Topic :: Text Processing
Provides-Extra: devel
